base_node_rpc/__init__.py
base_node_rpc/node.py
base_node_rpc/pavement_base.py
base_node_rpc/protobuf.py
base_node_rpc/proxy.py
base_node_rpc/queue.py
base_node_rpc/Arduino/base_node_rpc/Node.h
base_node_rpc/Arduino/base_node_rpc/NodeCommandProcessor.h
base_node_rpc/Arduino/base_node_rpc/RPCBuffer.h
base_node_rpc/Arduino/base_node_rpc/RPCBuffer.ht
base_node_rpc/Arduino/base_node_rpc/SConscript
base_node_rpc/Arduino/base_node_rpc/base_node_rpc.ino
base_node_rpc/Arduino/library/BaseNodeRpc.zip
base_node_rpc/Arduino/library/BaseNodeRpc/library.properties
base_node_rpc/Arduino/library/BaseNodeRpc/src/BaseNodeRpc.h
base_node_rpc/Arduino/library/BaseNodeRpc/src/BaseNodeRpc/BaseBuffer.h
base_node_rpc/Arduino/library/BaseNodeRpc/src/BaseNodeRpc/BaseHandler.h
base_node_rpc/Arduino/library/BaseNodeRpc/src/BaseNodeRpc/BaseNode.h
base_node_rpc/Arduino/library/BaseNodeRpc/src/BaseNodeRpc/BaseNodeConfig.h
base_node_rpc/Arduino/library/BaseNodeRpc/src/BaseNodeRpc/BaseNodeEeprom.h
base_node_rpc/Arduino/library/BaseNodeRpc/src/BaseNodeRpc/BaseNodeI2c.h
base_node_rpc/Arduino/library/BaseNodeRpc/src/BaseNodeRpc/BaseNodeI2cHandler.h
base_node_rpc/Arduino/library/BaseNodeRpc/src/BaseNodeRpc/BaseNodePb.h
base_node_rpc/Arduino/library/BaseNodeRpc/src/BaseNodeRpc/BaseNodeRpc.h
base_node_rpc/Arduino/library/BaseNodeRpc/src/BaseNodeRpc/BaseNodeSerialHandler.h
base_node_rpc/Arduino/library/BaseNodeRpc/src/BaseNodeRpc/BaseNodeSpi.h
base_node_rpc/Arduino/library/BaseNodeRpc/src/BaseNodeRpc/BaseNodeState.h
base_node_rpc/Arduino/library/BaseNodeRpc/src/BaseNodeRpc/CommandProcessor.h
base_node_rpc/Arduino/library/BaseNodeRpc/src/BaseNodeRpc/Commands.h
base_node_rpc/Arduino/library/BaseNodeRpc/src/BaseNodeRpc/I2cHandler.h
base_node_rpc/Arduino/library/BaseNodeRpc/src/BaseNodeRpc/Properties.h
base_node_rpc/Arduino/library/BaseNodeRpc/src/BaseNodeRpc/SerialHandler.h
base_node_rpc/bin/__init__.py
base_node_rpc/bin/upload.py
base_node_rpc-0.19.dist-info/DESCRIPTION.rst
base_node_rpc-0.19.dist-info/METADATA
base_node_rpc-0.19.dist-info/RECORD
base_node_rpc-0.19.dist-info/WHEEL
base_node_rpc-0.19.dist-info/metadata.json
base_node_rpc-0.19.dist-info/top_level.txt
